[
    {
        "id": 1,
        "author": "Pete Hunt",
        "text": "This is one comment"
    },
    {
        "id": 2,
        "author": "Jordan Walke",
        "text": "This is *another* comment"
    },
    {
        "id": 3,
        "author": "tessssss Hunt",
        "text": "This is one comment"
    },
    {
        "id": 1460557303619,
        "author": "aaa",
        "text": "aaaaaa"
    },
    {
        "id": 1460557307829,
        "author": "eeee",
        "text": "eeeeeeee"
    },
    {
        "id": 1460564077275,
        "author": "say someting",
        "text": "aaa"
    }
]